hello_pckg/__init__.py
hello_pckg/main.py
hello_pckg-0.2.dist-info/METADATA
hello_pckg-0.2.dist-info/WHEEL
hello_pckg-0.2.dist-info/entry_points.txt
hello_pckg-0.2.dist-info/top_level.txt
hello_pckg-0.2.dist-info/RECORD
