Metadata-Version: 2.1
Name: hello_pckg
Version: 0.2
Summary: Hello ouou!
Author: Omar
Author-email: omarfessy@gmail.com
